asyncpg/__init__.py
asyncpg/_version.py
asyncpg/cluster.py
asyncpg/compat.py
asyncpg/connect_utils.py
asyncpg/connection.py
asyncpg/connresource.py
asyncpg/cursor.py
asyncpg/introspection.py
asyncpg/pool.py
asyncpg/prepared_stmt.py
asyncpg/serverversion.py
asyncpg/transaction.py
asyncpg/types.py
asyncpg/utils.py
asyncpg/_testbase/__init__.py
asyncpg/_testbase/fuzzer.py
asyncpg/exceptions/__init__.py
asyncpg/exceptions/_base.py
asyncpg/pgproto/__init__.pxd
asyncpg/pgproto/__init__.py
asyncpg/pgproto/buffer.pxd
asyncpg/pgproto/buffer.pyx
asyncpg/pgproto/consts.pxi
asyncpg/pgproto/cpythonx.pxd
asyncpg/pgproto/debug.pxd
asyncpg/pgproto/frb.pxd
asyncpg/pgproto/frb.pyx
asyncpg/pgproto/hton.pxd
asyncpg/pgproto/pgproto.cpython-311-darwin.so
asyncpg/pgproto/pgproto.pxd
asyncpg/pgproto/pgproto.pyx
asyncpg/pgproto/tohex.pxd
asyncpg/pgproto/types.py
asyncpg/pgproto/uuid.pyx
asyncpg/protocol/__init__.py
asyncpg/protocol/consts.pxi
asyncpg/protocol/coreproto.pxd
asyncpg/protocol/coreproto.pyx
asyncpg/protocol/cpythonx.pxd
asyncpg/protocol/encodings.pyx
asyncpg/protocol/pgtypes.pxi
asyncpg/protocol/prepared_stmt.pxd
asyncpg/protocol/prepared_stmt.pyx
asyncpg/protocol/protocol.cpython-311-darwin.so
asyncpg/protocol/protocol.pxd
asyncpg/protocol/protocol.pyx
asyncpg/protocol/scram.pxd
asyncpg/protocol/scram.pyx
asyncpg/protocol/settings.pxd
asyncpg/protocol/settings.pyx
asyncpg/protocol/codecs/__init__.py
asyncpg/protocol/codecs/array.pyx
asyncpg/protocol/codecs/base.pxd
asyncpg/protocol/codecs/base.pyx
asyncpg/protocol/codecs/pgproto.pyx
asyncpg/protocol/codecs/range.pyx
asyncpg/protocol/codecs/record.pyx
asyncpg/protocol/codecs/textutils.pyx
asyncpg_dev-0.28.0.dev1.dist-info/AUTHORS
asyncpg_dev-0.28.0.dev1.dist-info/LICENSE
asyncpg_dev-0.28.0.dev1.dist-info/METADATA
asyncpg_dev-0.28.0.dev1.dist-info/WHEEL
asyncpg_dev-0.28.0.dev1.dist-info/top_level.txt
asyncpg_dev-0.28.0.dev1.dist-info/RECORD
