Metadata-Version: 2.1
Name: asyncpg-dev
Version: 0.28.0.dev1
Summary: An asyncio PostgreSQL driver
Home-page: https://github.com/MagicStack/asyncpg
Author: MagicStack Inc
Author-email: hello@magic.io
License: Apache License, Version 2.0
Platform: macOS
Platform: POSIX
Platform: Windows
Classifier: Development Status :: 5 - Production/Stable
Classifier: Framework :: AsyncIO
Classifier: Intended Audience :: Developers
Classifier: License :: OSI Approved :: Apache Software License
Classifier: Operating System :: POSIX
Classifier: Operating System :: MacOS :: MacOS X
Classifier: Operating System :: Microsoft :: Windows
Classifier: Programming Language :: Python :: 3 :: Only
Classifier: Programming Language :: Python :: 3.7
Classifier: Programming Language :: Python :: 3.8
Classifier: Programming Language :: Python :: 3.9
Classifier: Programming Language :: Python :: 3.10
Classifier: Programming Language :: Python :: Implementation :: CPython
Classifier: Topic :: Database :: Front-Ends
Requires-Python: >=3.7.0
License-File: LICENSE
License-File: AUTHORS
Requires-Dist: typing-extensions (>=3.7.4.3) ; python_version < "3.8"
Provides-Extra: dev
Requires-Dist: Cython (<0.30.0,>=0.29.24) ; extra == 'dev'
Requires-Dist: pytest (>=6.0) ; extra == 'dev'
Requires-Dist: Sphinx (~=4.1.2) ; extra == 'dev'
Requires-Dist: sphinxcontrib-asyncio (~=0.3.0) ; extra == 'dev'
Requires-Dist: sphinx-rtd-theme (~=0.5.2) ; extra == 'dev'
Requires-Dist: flake8 (~=5.0.4) ; extra == 'dev'
Requires-Dist: uvloop (>=0.15.3) ; (platform_system != "Windows") and extra == 'dev'
Provides-Extra: docs
Requires-Dist: Sphinx (~=4.1.2) ; extra == 'docs'
Requires-Dist: sphinxcontrib-asyncio (~=0.3.0) ; extra == 'docs'
Requires-Dist: sphinx-rtd-theme (~=0.5.2) ; extra == 'docs'
Provides-Extra: test
Requires-Dist: flake8 (~=5.0.4) ; extra == 'test'
Requires-Dist: uvloop (>=0.15.3) ; (platform_system != "Windows") and extra == 'test'
